whatshap-2.8.dist-info/top_level.txt
whatshap-2.8.dist-info/RECORD
whatshap-2.8.dist-info/METADATA
whatshap-2.8.dist-info/entry_points.txt
whatshap-2.8.dist-info/WHEEL
whatshap-2.8.dist-info/licenses/LICENSE
whatshap/_variants.pyi
whatshap/variants.py
whatshap/testhelpers.py
whatshap/merge.py
whatshap/__main__.py
whatshap/phred_scores.py
whatshap/bam.py
whatshap/utils.py
whatshap/_variants.pyx
whatshap/priorityqueue.pxd
whatshap/priorityqueue.pyi
whatshap/cpp.pxd
whatshap/vcf.py
whatshap/core.pyx
whatshap/align.pyx
whatshap/__init__.py
whatshap/.gitignore
whatshap/timer.py
whatshap/variant.py
whatshap/core.cpython-310-x86_64-linux-gnu.so
whatshap/priorityqueue.pyx
whatshap/_variants.cpython-310-x86_64-linux-gnu.so
whatshap/readselect.cpython-310-x86_64-linux-gnu.so
whatshap/types.py
whatshap/args.py
whatshap/verification.py
whatshap/core.pyi
whatshap/coverage.py
whatshap/readselect.pyi
whatshap/align.cpython-310-x86_64-linux-gnu.so
whatshap/graph.py
whatshap/align.pyi
whatshap/readselect.pyx
whatshap/_version.py
whatshap/pedigree.py
whatshap/core.pxd
whatshap/priorityqueue.cpython-310-x86_64-linux-gnu.so
whatshap/polyphase/reorder.py
whatshap/polyphase/algorithm.py
whatshap/polyphase/solver.cpp
whatshap/polyphase/offspringscoring.py
whatshap/polyphase/__init__.py
whatshap/polyphase/clusterarrangement.py
whatshap/polyphase/plots.py
whatshap/polyphase/variantselection.py
whatshap/polyphase/solver.cpython-310-x86_64-linux-gnu.so
whatshap/polyphase/solver.pxd
whatshap/polyphase/solver.pyi
whatshap/polyphase/threading.py
whatshap/polyphase/solver.pyx
whatshap/cli/compare.py
whatshap/cli/haplotag.py
whatshap/cli/polyphasegenetic.py
whatshap/cli/polyphase.py
whatshap/cli/haplotagphase.py
whatshap/cli/phase.py
whatshap/cli/stats.py
whatshap/cli/__init__.py
whatshap/cli/split.py
whatshap/cli/hapcut2vcf.py
whatshap/cli/unphase.py
whatshap/cli/genotype.py
whatshap/cli/learn.py
whatshap/cli/find_snv_candidates.py
