Metadata-Version: 2.4
Name: whatshap
Version: 2.8
Summary: phase genomic variants using DNA sequencing reads
Author: WhatsHap authors
License-Expression: MIT
Project-URL: Homepage, https://github.com/whatshap/whatshap
Project-URL: Changelog, https://whatshap.readthedocs.io/en/latest/changes.html
Classifier: Development Status :: 5 - Production/Stable
Classifier: Environment :: Console
Classifier: Intended Audience :: Science/Research
Classifier: Programming Language :: Cython
Classifier: Programming Language :: Python :: 3
Classifier: Topic :: Scientific/Engineering :: Bio-Informatics
Requires-Python: >=3.9
License-File: LICENSE
Requires-Dist: pysam>=0.18.0
Requires-Dist: pyfaidx>=0.5.5.2
Requires-Dist: networkx
Requires-Dist: biopython>=1.73
Requires-Dist: scipy
Requires-Dist: xopen>=1.2.0
Requires-Dist: pulp>=2
Provides-Extra: dev
Requires-Dist: Cython; extra == "dev"
Requires-Dist: pytest; extra == "dev"
Requires-Dist: hypothesis; extra == "dev"
Requires-Dist: sphinx>=4.4; extra == "dev"
Requires-Dist: sphinx-issues; extra == "dev"
Requires-Dist: pysam-stubs; extra == "dev"
Provides-Extra: docs
Requires-Dist: sphinx<7; extra == "docs"
Requires-Dist: sphinx_rtd_theme; extra == "docs"
Requires-Dist: sphinx-issues; extra == "docs"
Requires-Dist: sphinx_better_subsection; extra == "docs"
Dynamic: license-file
